couchstore.py
setup.py
couchstore.egg-info/PKG-INFO
couchstore.egg-info/SOURCES.txt
couchstore.egg-info/dependency_links.txt
couchstore.egg-info/top_level.txt