Metadata-Version: 1.0
Name: couchstore
Version: 0.1
Summary: Re-usable bindings for couchstore library
Home-page: UNKNOWN
Author: Couchbase, Inc.
Author-email: UNKNOWN
License: UNKNOWN
Platform: UNKNOWN
